randgen/__init__.py
randgen/example.py
randgen-1.0.1.dist-info/LICENSE
randgen-1.0.1.dist-info/METADATA
randgen-1.0.1.dist-info/WHEEL
randgen-1.0.1.dist-info/top_level.txt
randgen-1.0.1.dist-info/RECORD
