Metadata-Version: 2.1
Name: randgen
Version: 1.0.1
Summary: A Random Generator for Multiple Scenarios
Author-email: hrhszsdtc <hrhszsdtc@outlook.com>
License: GNU GENERAL PUBLIC LICENSE
Project-URL: Homepage, https://github.com/hrhszsdtc/py-random-generator
Project-URL: Bug Tracker, https://github.com/hrhszsdtc/py-random-generator/issues
Keywords: random,generator
Classifier: Programming Language :: Python :: 3
Requires-Python: >=3.9
License-File: LICENSE
